warpxio/__init__.py
warpxio/cli.py
warpxio-0.1.1.dist-info/METADATA
warpxio-0.1.1.dist-info/WHEEL
warpxio-0.1.1.dist-info/entry_points.txt
warpxio-0.1.1.dist-info/top_level.txt
warpxio-0.1.1.dist-info/RECORD
