Metadata-Version: 2.4
Name: warpxio
Version: 0.1.1
Summary: A CLI-based AI text generation tool (Proprietary)
Author-email: Roni Bhakta <ronibhakta1@gmail.com>
License: Proprietary
Classifier: Development Status :: 3 - Alpha
Classifier: Intended Audience :: Developers
Classifier: Programming Language :: Python :: 3
Classifier: Programming Language :: Python :: 3.8
Classifier: Programming Language :: Python :: 3.9
Classifier: Programming Language :: Python :: 3.10
Classifier: Programming Language :: Python :: 3.11
Classifier: Programming Language :: Python :: 3.12
Classifier: Programming Language :: Python :: 3.13
Classifier: Operating System :: OS Independent
Requires-Python: >=3.8
Requires-Dist: click>=8.2.1
